LICENSE
MANIFEST.in
README.md
pyproject.toml
requirements.txt
setup.py
requirements/dev.txt
requirements/docs.txt
requirements/speedup.txt
src/tankioapi.egg-info/PKG-INFO
src/tankioapi.egg-info/SOURCES.txt
src/tankioapi.egg-info/dependency_links.txt
src/tankioapi.egg-info/requires.txt
src/tankioapi.egg-info/top_level.txt
src/toapi/__init__.py
src/toapi/client.py
src/toapi/errors.py
src/toapi/http.py
src/toapi/py.typed
src/toapi/data/__init__.py
src/toapi/data/ranks.py
src/toapi/data/test_server.py
src/toapi/types/__init__.py
src/toapi/types/game_object.py
src/toapi/types/mode.py
src/toapi/types/rank.py
src/toapi/types/rating.py
src/toapi/types/status.py
src/toapi/types/top.py
src/toapi/types/user.py