Metadata-Version: 2.1
Name: tankioapi
Version: 1.0.1
Summary: A Python written wrapper for the Tanki Online game API
Home-page: https://github.com/stngularity/tankioapi
Author: stngularity
Author-email: stngularity <stngularity@gmail.com>
License: MIT License
Project-URL: Documentation, https://stngularity.github.io/tankioapi
Project-URL: Homepage, https://github.com/stngularity/tankioapi
Project-URL: Source Code, https://github.com/stngularity/tankioapi
Project-URL: Changelog, https://github.com/stngularity/tankioapi/blob/main/CHANGELOG.md
Project-URL: Bug Tracker, https://github.com/stngularity/tankioapi/issues
Keywords: game,api,to,tanki online
Classifier: Development Status :: 5 - Production/Stable
Classifier: License :: OSI Approved :: MIT License
Classifier: Natural Language :: English
Classifier: Operating System :: OS Independent
Classifier: Programming Language :: Python
Classifier: Programming Language :: Python :: 3 :: Only
Classifier: Programming Language :: Python :: 3.8
Classifier: Programming Language :: Python :: 3.9
Classifier: Programming Language :: Python :: 3.10
Classifier: Programming Language :: Python :: 3.11
Classifier: Programming Language :: Python :: Implementation :: CPython
Classifier: Topic :: Utilities
Classifier: Typing :: Typed
Requires-Python: >=3.8
Provides-Extra: speedup
Provides-Extra: dev
License-File: LICENSE
